exfoliate/VERSION.txt
exfoliate/__init__.py
exfoliate/exfoliate.py
exfoliate-0.0.4.dist-info/DESCRIPTION.rst
exfoliate-0.0.4.dist-info/METADATA
exfoliate-0.0.4.dist-info/RECORD
exfoliate-0.0.4.dist-info/WHEEL
exfoliate-0.0.4.dist-info/metadata.json
exfoliate-0.0.4.dist-info/top_level.txt
